murano_client/Murano_Root_CA.cer
murano_client/__init__.py
murano_client/__version__.py
murano_client/client.py
murano_client/constants.py
murano_client/gdc.py
murano_client/http.py
murano_client/ini.py
murano_client/logger.py
murano_client/mqtt.py
murano_client/atomicconfigparser/__init__.py
murano_client/commands/__init__.py
murano_client/commands/cfg.py
murano_client/commands/http/__init__.py
murano_client/commands/http/activate.py
murano_client/commands/http/content.py
murano_client/commands/http/poll.py
murano_client/commands/http/read.py
murano_client/commands/http/record.py
murano_client/commands/http/timestamp.py
murano_client/commands/http/write.py
murano_client/commands/mqtt/__init__.py
murano_client/commands/mqtt/activate.py
murano_client/commands/mqtt/publish.py
murano_client/commands/mqtt/pubsub.py
murano_client/commands/mqtt/subscribe.py
test/__init__.py
test/test_client.py
test/test_constructors.py
test/test_long_poll.py
test/test_oubound_payloads.py
murano_client-21.12.22.dist-info/LICENSE
murano_client-21.12.22.dist-info/METADATA
murano_client-21.12.22.dist-info/WHEEL
murano_client-21.12.22.dist-info/entry_points.txt
murano_client-21.12.22.dist-info/top_level.txt
murano_client-21.12.22.dist-info/RECORD
