Metadata-Version: 2.1
Name: murano-client
Version: 21.12.22
Summary: Murano Device Client is the primary library for communicating with the Exosite Murano Platform.
Home-page: https://github.com/exosite/lib_murano_client_python
Author: Exosite LLC
Author-email: support@exosite.com
License: Apache 2.0
Keywords: murano exosite iot iiot client gateway
Platform: UNKNOWN
Classifier: Development Status :: 4 - Beta
Classifier: Programming Language :: Python :: 2.7
Classifier: Programming Language :: Python :: 3.4
Classifier: Programming Language :: Python :: 3.5
Classifier: Programming Language :: Python :: 3.6
Classifier: Operating System :: POSIX :: Linux
Classifier: Topic :: System :: Operating System Kernels :: Linux
Classifier: Topic :: Software Development :: Embedded Systems
Classifier: License :: OSI Approved :: Apache Software License
Requires-Python: <4,>=2.7.9
License-File: LICENSE
Requires-Dist: docopt (>=0.6.2)
Requires-Dist: requests (>=2.13.0)
Requires-Dist: paho-mqtt
Requires-Dist: six
